{
  "kind": "singleType",
  "collectionName": "texts",
  "info": {
    "singularName": "text",
    "pluralName": "texts",
    "displayName": "Text"
  },
  "options": {
    "draftAndPublish": false
  },
  "pluginOptions": {
    "i18n": {
      "localized": true
    }
  },
  "attributes": {
    "services": {
      "pluginOptions": {
        "i18n": {
          "localized": true
        }
      },
      "type": "string"
    },
    "scopes": {
      "pluginOptions": {
        "i18n": {
          "localized": true
        }
      },
      "type": "string"
    },
    "capabilities": {
      "pluginOptions": {
        "i18n": {
          "localized": true
        }
      },
      "type": "string"
    }
  }
}
